dynadoc/__init__.py
dynadoc/assembly.py
dynadoc/context.py
dynadoc/factories.py
dynadoc/interfaces.py
dynadoc/introspection.py
dynadoc/nomina.py
dynadoc/py.typed
dynadoc/userapi.py
dynadoc/xtnsapi.py
dynadoc/__/__init__.py
dynadoc/__/doctab.py
dynadoc/__/imports.py
dynadoc/__/nomina.py
dynadoc/renderers/__.py
dynadoc/renderers/__init__.py
dynadoc/renderers/sphinxad.py
dynadoc-1.4.dist-info/METADATA
dynadoc-1.4.dist-info/WHEEL
dynadoc-1.4.dist-info/licenses/LICENSE.txt
dynadoc-1.4.dist-info/RECORD
