Metadata-Version: 2.4
Name: dynadoc
Version: 1.4
Summary: Docstring generation from annotations with configurable output formats.
Project-URL: Homepage, https://github.com/emcd/python-dynadoc
Project-URL: Documentation, https://emcd.github.io/python-dynadoc
Project-URL: Download, https://pypi.org/project/dynadoc/#files
Project-URL: Source Code, https://github.com/emcd/python-dynadoc
Project-URL: Issue Tracker, https://github.com/emcd/python-dynadoc/issues
Author-email: Eric McDonald <emcd@users.noreply.github.com>
License-Expression: Apache-2.0
License-File: LICENSE.txt
Keywords: PEP 727,annotations,docstring,dynamic,introspection
Classifier: Development Status :: 5 - Production/Stable
Classifier: Intended Audience :: Developers
Classifier: License :: OSI Approved :: Apache Software License
Classifier: Programming Language :: Python :: 3 :: Only
Classifier: Programming Language :: Python :: 3.10
Classifier: Programming Language :: Python :: 3.11
Classifier: Programming Language :: Python :: 3.12
Classifier: Programming Language :: Python :: 3.13
Classifier: Programming Language :: Python :: Implementation :: CPython
Classifier: Programming Language :: Python :: Implementation :: PyPy
Classifier: Topic :: Software Development
Requires-Python: >=3.10
Requires-Dist: typing-extensions
